trivial_torch_tools/__init__.py
trivial_torch_tools/core.py
trivial_torch_tools/generics.py
trivial_torch_tools/image.py
trivial_torch_tools/main.py
trivial_torch_tools/misc.py
trivial_torch_tools/model.py
trivial_torch_tools/one_hots.py
trivial_torch_tools/settings.json
trivial_torch_tools/__dependencies__/__init__.py
trivial_torch_tools/__dependencies__/__pycache__/__init__.cpython-38.pyc
trivial_torch_tools/__dependencies__/__sources__/file_system_py/.gitignore
trivial_torch_tools/__dependencies__/__sources__/file_system_py/.gitrepo
trivial_torch_tools/__dependencies__/__sources__/file_system_py/README.md
trivial_torch_tools/__dependencies__/__sources__/file_system_py/poetry.lock
trivial_torch_tools/__dependencies__/__sources__/file_system_py/pyproject.toml
trivial_torch_tools/__dependencies__/__sources__/file_system_py/commands/pip
trivial_torch_tools/__dependencies__/__sources__/file_system_py/commands/shell
trivial_torch_tools/__dependencies__/__sources__/file_system_py/commands/start
trivial_torch_tools/__dependencies__/__sources__/file_system_py/commands/subrepo
trivial_torch_tools/__dependencies__/__sources__/file_system_py/commands/project/clean
trivial_torch_tools/__dependencies__/__sources__/file_system_py/commands/project/commands
trivial_torch_tools/__dependencies__/__sources__/file_system_py/commands/project/local_install
trivial_torch_tools/__dependencies__/__sources__/file_system_py/commands/project/publish
trivial_torch_tools/__dependencies__/__sources__/file_system_py/commands/project/purge
trivial_torch_tools/__dependencies__/__sources__/file_system_py/documentation/fornix_framework.md
trivial_torch_tools/__dependencies__/__sources__/file_system_py/documentation/setup.md
trivial_torch_tools/__dependencies__/__sources__/file_system_py/documentation/images/cd_tutorial.gif
trivial_torch_tools/__dependencies__/__sources__/file_system_py/documentation/images/package_from_example.png
trivial_torch_tools/__dependencies__/__sources__/super_hash/main/super_hash.egg-info/PKG-INFO
trivial_torch_tools/__dependencies__/__sources__/super_hash/main/super_hash.egg-info/SOURCES.txt
trivial_torch_tools/__dependencies__/__sources__/super_hash/main/super_hash.egg-info/dependency_links.txt
trivial_torch_tools/__dependencies__/__sources__/super_hash/main/super_hash.egg-info/top_level.txt
trivial_torch_tools-0.6.4.dist-info/METADATA
trivial_torch_tools-0.6.4.dist-info/WHEEL
trivial_torch_tools-0.6.4.dist-info/top_level.txt
trivial_torch_tools-0.6.4.dist-info/RECORD
