Metadata-Version: 2.1
Name: trivial-torch-tools
Version: 0.6.4
Summary: Decorators for reducing pytorch boilerplate
Home-page: https://github.com/jeff-hykin/trivial-torch-tools.git
Author: Jeff Hykin
Author-email: jeff.hykin@gmail.com
License: MIT
Platform: UNKNOWN
Requires-Python: >=3.6
Requires-Dist: torchvision (>=0.9.0)
